<?xml version="1.0" encoding="utf-8" ?>
<dwsync>
<file name="20121201.jpg" server="210.209.114.18/web/" local="130538815432723257" remote="130537938000000000" Dst="0" />
<file name="20121202.jpg" server="210.209.114.18/web/" local="130538815458954757" remote="130537938000000000" Dst="0" />
<file name="20121204.jpg" server="210.209.114.18/web/" local="130538815478375868" remote="130537938600000000" Dst="0" />
<file name="20121203.JPG" server="210.209.114.18/web/" local="130538815494786807" remote="130537938000000000" Dst="0" />
<file name="20121205.jpg" server="210.209.114.18/web/" local="130538815514587939" remote="130537938600000000" Dst="0" />
<file name="20121206.jpg" server="210.209.114.18/web/" local="130538815517078082" remote="130537939200000000" Dst="0" />
<file name="20121207.jpg" server="210.209.114.18/web/" local="130538815521818353" remote="130537938600000000" Dst="0" />
<file name="20121208.jpg" server="210.209.114.18/web/" local="130538815554970249" remote="130537938600000000" Dst="0" />
</dwsync>